[
  {
    "firm": "Cavendish Property Investments Ltd (Postcode: LS7 4NB) ",
    "fca_link": "https://register.fca.org.uk/ShPo_FirmDetailsPage?id=001b000000MfRPMAA3",
    "trading_names": "Cavendish Equity Release,Equity Release Information Centre,CGA Protect,AskEric,Ask Eric Annuity Services,Cavendish Annuity Services",
    "ref_number": "302589",
    "status": "Authorised"
  },
  {
    "firm": "P A Asset Management LLP (Postcode: LS7 3QB) ",
    "fca_link": "https://register.fca.org.uk/ShPo_FirmDetailsPage?id=001b000000MfVrIAAV",
    "ref_number": "401741",
    "status": "Authorised"
  },
  {
    "firm": "Handley Gibson (Postcode: LS7 3AF) ",
    "fca_link": "https://register.fca.org.uk/ShPo_FirmDetailsPage?id=001b000000MfT81AAF",
    "trading_names": "Handley Gibson Twaites",
    "ref_number": "314863",
    "status": "Authorised"
  },
  {
    "firm": "BMF Limited (Postcode: LS7 2HZ) ",
    "fca_link": "https://register.fca.org.uk/ShPo_FirmDetailsPage?id=001b000003F4tNhAAJ",
    "trading_names": "www.bmfstore.co.uk,www.stovesaver.co.uk",
    "ref_number": "731807",
    "status": "Authorised"
  },
  {
    "firm": "TPFA Limited (Postcode: LS7 4RF) ",
    "fca_link": "https://register.fca.org.uk/ShPo_FirmDetailsPage?id=001b000000NMhLzAAL",
    "trading_names": "The Financial Advice Company",
    "ref_number": "611188",
    "status": "Authorised"
  },
  {
    "firm": "Manku Construction Limited (Postcode: LS7 1AQ) ",
    "fca_link": "https://register.fca.org.uk/ShPo_FirmDetailsPage?id=001b000000RxMOUAA3",
    "trading_names": "Manku Energy Savers,Kulrads",
    "ref_number": "622129",
    "status": "Authorised"
  },
  {
    "firm": "Yoozom telecom Ltd (Postcode: LS7 3JB) ",
    "fca_link": "https://register.fca.org.uk/ShPo_FirmDetailsPage?id=001b000003F5M1QAAV",
    "ref_number": "732131",
    "status": "Authorised"
  },
  {
    "firm": "Q.L.M (LEEDS) LIMITED (Postcode: LS7 2TT) ",
    "fca_link": "https://register.fca.org.uk/ShPo_FirmDetailsPage?id=001b000000h6cIyAAI",
    "trading_names": "QLM HOUSE AND HOME,QLMBED.COM",
    "ref_number": "660561",
    "status": "Authorised"
  },
  {
    "firm": "basewheel ltd (Postcode: LS7 2RE) ",
    "fca_link": "https://register.fca.org.uk/ShPo_FirmDetailsPage?id=001b000001m21sGAAQ",
    "trading_names": "Kelvin World of Furniture",
    "ref_number": "723088",
    "status": "Authorised"
  },
  {
    "firm": "FOUR PLUS 4 LIMITED (Postcode: LS7 2BX) ",
    "fca_link": "https://register.fca.org.uk/ShPo_FirmDetailsPage?id=001b000000h6UMwAAM",
    "ref_number": "660452",
    "status": "Authorised"
  },
  {
    "firm": "Morris Financial Planning Limited (Postcode: LS7 4RF) ",
    "fca_link": "https://register.fca.org.uk/ShPo_FirmDetailsPage?id=001b000000NMHywAAH",
    "ref_number": "562057",
    "status": "Authorised"
  },
  {
    "firm": "Provac Sales Ltd (Postcode: LS7 1RQ) ",
    "fca_link": "https://register.fca.org.uk/ShPo_FirmDetailsPage?id=001b0000015mBulAAE",
    "ref_number": "712914",
    "status": "Authorised"
  },
  {
    "firm": "Sunuser Limited (Postcode: LS7 2DQ) ",
    "fca_link": "https://register.fca.org.uk/ShPo_FirmDetailsPage?id=001b000000k2NcaAAE",
    "ref_number": "670525",
    "status": "Authorised"
  },
  {
    "firm": "Thundercity Motorcycles Limited (Postcode: LS7 1QQ) ",
    "fca_link": "https://register.fca.org.uk/ShPo_FirmDetailsPage?id=001b000000h45r0AAA",
    "ref_number": "657369",
    "status": "Authorised"
  },
  {
    "firm": "Chapeltown Citizens Advice Bureau (Postcode: LS7 4BZ) ",
    "fca_link": "https://register.fca.org.uk/ShPo_FirmDetailsPage?id=001b000000P6Sn7AAF",
    "trading_names": "CHAPELTOWN CITIZENS ADVICE BUREAU",
    "ref_number": "617547",
    "status": "Authorised"
  },
  {
    "firm": "Chapel Allerton Lawn Tennis and Squash Club (Postcode: LS7 3QX) ",
    "fca_link": "https://register.fca.org.uk/ShPo_FirmDetailsPage?id=001b000003HUb6GAAT",
    "ref_number": "734726",
    "status": "Authorised"
  },
  {
    "firm": "Ridings Reprographics Limited (Postcode: LS7 2JF) ",
    "fca_link": "https://register.fca.org.uk/ShPo_FirmDetailsPage?id=001b000000j27qQAAQ",
    "ref_number": "667046",
    "status": "Authorised"
  },
  {
    "firm": "The Copier Company UK Ltd (Postcode: LS7 2BP) ",
    "fca_link": "https://register.fca.org.uk/ShPo_FirmDetailsPage?id=001b000001z8U5lAAE",
    "ref_number": "723588",
    "status": "Authorised"
  }
]