[
  {
    "firm": "Next Step Mortgages Ltd (Postcode: N17 6QH) ",
    "fca_link": "https://register.fca.org.uk/ShPo_FirmDetailsPage?id=001b000000MfSV7AAN",
    "ref_number": "303850",
    "status": "Authorised"
  },
  {
    "firm": "Chiller Box Ltd (Postcode: N17 8DP) ",
    "fca_link": "https://register.fca.org.uk/ShPo_FirmDetailsPage?id=001b000002C5VwxAAF",
    "ref_number": "725815",
    "status": "Authorised"
  },
  {
    "firm": "Welwitschia Welfare Centre (Postcode: N17 0SP) ",
    "fca_link": "https://register.fca.org.uk/ShPo_FirmDetailsPage?id=001b000000R80omAAB",
    "trading_names": "Welwitschia Welfare Centre",
    "ref_number": "618873",
    "status": "Authorised"
  },
  {
    "firm": "Haringey Law Centre (Postcode: N17 9AA) ",
    "fca_link": "https://register.fca.org.uk/ShPo_FirmDetailsPage?id=001b000000P6SqyAAF",
    "trading_names": "Haringey Law Centre",
    "ref_number": "617405",
    "status": "Authorised"
  },
  {
    "firm": "kamil furniture (london) ltd (Postcode: N17 7QY) ",
    "fca_link": "https://register.fca.org.uk/ShPo_FirmDetailsPage?id=001b000000qJX6OAAW",
    "trading_names": "SERHAT MOBILYA,serhat furniture",
    "ref_number": "706462",
    "status": "Authorised"
  },
  {
    "firm": "The Modish Group Ltd (Postcode: N17 8JG) ",
    "fca_link": "https://register.fca.org.uk/ShPo_FirmDetailsPage?id=001b0000025Q5JHAA0",
    "trading_names": "Modish Energy",
    "ref_number": "724609",
    "status": "Authorised"
  },
  {
    "firm": "M-Press Imaging Systems Limited (Postcode: N17 8DP) ",
    "fca_link": "https://register.fca.org.uk/ShPo_FirmDetailsPage?id=001b000001YWfYsAAL",
    "ref_number": "719128",
    "status": "Authorised"
  },
  {
    "firm": "Champion Hire (London) Ltd (Postcode: N17 0SQ) ",
    "fca_link": "https://register.fca.org.uk/ShPo_FirmDetailsPage?id=001b000001MVLT7AAP",
    "ref_number": "716082",
    "status": "Authorised"
  },
  {
    "firm": "Embrace UK Community Support Centre (Postcode: N17 8JL) ",
    "fca_link": "https://register.fca.org.uk/ShPo_FirmDetailsPage?id=001b000000R80qZAAR",
    "trading_names": "Embrace UK Community Support Centre",
    "ref_number": "618750",
    "status": "Authorised"
  },
  {
    "firm": "Best Contract Cars LTD (Postcode: N17 8ER) ",
    "fca_link": "https://register.fca.org.uk/ShPo_FirmDetailsPage?id=001b0000015ngsWAAQ",
    "trading_names": "Best Contract Cars",
    "ref_number": "713398",
    "status": "Authorised"
  },
  {
    "firm": "COMMERCIAL VEHICLE SALES (TOTTENHAM) LIMITED (Postcode: N17 8HP) ",
    "fca_link": "https://register.fca.org.uk/ShPo_FirmDetailsPage?id=001b000000j32JDAAY",
    "ref_number": "667971",
    "status": "Authorised"
  },
  {
    "firm": "White Hart Lane Stadium Ltd (Postcode: N17 0AP) ",
    "fca_link": "https://register.fca.org.uk/ShPo_FirmDetailsPage?id=001b000000m6pItAAI",
    "trading_names": "Tottenham Hotspur FC,Tottenhamhotspur.com",
    "ref_number": "681211",
    "status": "Authorised"
  },
  {
    "firm": "London Adventist Credit Union Limited (Postcode: N17 9AD) ",
    "fca_link": "https://register.fca.org.uk/ShPo_FirmDetailsPage?id=001b000000MfM7hAAF",
    "trading_names": "North London Adventist Credit Union Limited",
    "ref_number": "213267",
    "status": "Authorised"
  },
  {
    "firm": "Tottenham Hotspur Football & Athletic Co Limited (Postcode: N17 0BX) ",
    "fca_link": "https://register.fca.org.uk/ShPo_FirmDetailsPage?id=001b000000m6pImAAI",
    "trading_names": "Tottenham Hotspur FC,Tottenhamhotspur.com",
    "ref_number": "681200",
    "status": "Authorised"
  }
]