[
  {
    "firm": "West Bromwich Building Society (Postcode: B70 8AF) ",
    "fca_link": "https://register.fca.org.uk/ShPo_FirmDetailsPage?id=001b000000MfEvIAAV",
    "trading_names": "The West Brom,the West Brom",
    "ref_number": "104877",
    "status": "Authorised"
  },
  {
    "firm": "Friends Advisers Ltd (Postcode: B70 9LD) ",
    "fca_link": "https://register.fca.org.uk/ShPo_FirmDetailsPage?id=001b000002NHn0rAAD",
    "trading_names": "Friends Financial Advisers",
    "ref_number": "726600",
    "status": "Authorised"
  },
  {
    "firm": "6 Towns Credit Union Limited (Postcode: B70 6LB) ",
    "fca_link": "https://register.fca.org.uk/ShPo_FirmDetailsPage?id=001b000000Mfav2AAB",
    "ref_number": "419396",
    "status": "Authorised"
  },
  {
    "firm": "J.Sydney Ault Ltd (Postcode: B70 8SD) ",
    "fca_link": "https://register.fca.org.uk/ShPo_FirmDetailsPage?id=001b000000MfPtEAAV",
    "trading_names": "Swimsure,Ault Insurance Brokers",
    "ref_number": "311469",
    "status": "Authorised"
  },
  {
    "firm": "Napier-Munroe Ltd (Postcode: B70 0PU) ",
    "fca_link": "https://register.fca.org.uk/ShPo_FirmDetailsPage?id=001b000000m6RV8AAM",
    "ref_number": "680133",
    "status": "Authorised"
  },
  {
    "firm": "YESMAR RESTAURANTS LTD (Postcode: B70 7QG) ",
    "fca_link": "https://register.fca.org.uk/ShPo_FirmDetailsPage?id=001b000000k49RiAAI",
    "trading_names": "McDonald's",
    "ref_number": "671799",
    "status": "Authorised"
  },
  {
    "firm": "sandwell car sales (Postcode: B70 9EN) ",
    "fca_link": "https://register.fca.org.uk/ShPo_FirmDetailsPage?id=001b000000ekI3tAAE",
    "ref_number": "652360",
    "status": "Authorised"
  },
  {
    "firm": "Sandwell Citizens Advice Bureau (Postcode: B70 8RT) ",
    "fca_link": "https://register.fca.org.uk/ShPo_FirmDetailsPage?id=001b000000P6Sw0AAF",
    "trading_names": "SANDWELL CITIZENS ADVICE BUREAUX",
    "ref_number": "617724",
    "status": "Authorised"
  },
  {
    "firm": "Sandwell Garages Limited (Postcode: B70 6AR) ",
    "fca_link": "https://register.fca.org.uk/ShPo_FirmDetailsPage?id=001b000000MfVlaAAF",
    "ref_number": "307335",
    "status": "Authorised"
  },
  {
    "firm": "Richie Sudera (Postcode: B70 6JW) ",
    "fca_link": "https://register.fca.org.uk/ShPo_FirmDetailsPage?id=001b000003ILqRbAAL",
    "ref_number": "736555",
    "status": "Authorised"
  },
  {
    "firm": "Czech-Pol Limited (Postcode: B70 9QG) ",
    "fca_link": "https://register.fca.org.uk/ShPo_FirmDetailsPage?id=001b000000R80nEAAR",
    "trading_names": "Medical-Dent,www.dentystabirmingham.co.uk",
    "ref_number": "619628",
    "status": "Authorised"
  },
  {
    "firm": "Alpha Floor Maintenance Equipment (Postcode: B70 0AX) ",
    "fca_link": "https://register.fca.org.uk/ShPo_FirmDetailsPage?id=001b000000m6SfqAAE",
    "ref_number": "680684",
    "status": "Authorised"
  },
  {
    "firm": "Confederation of Bangladeshi Organisations (cbo)limited (Postcode: B70 9JF) ",
    "fca_link": "https://register.fca.org.uk/ShPo_FirmDetailsPage?id=001b000000qHTTjAAO",
    "trading_names": "CBO",
    "ref_number": "705620",
    "status": "Authorised"
  },
  {
    "firm": "Langley Business Systems (Retail) Limited (Postcode: B70 8JN) ",
    "fca_link": "https://register.fca.org.uk/ShPo_FirmDetailsPage?id=001b000000pio53AAA",
    "ref_number": "702806",
    "status": "Authorised"
  },
  {
    "firm": "West Bromwich Mortgage Company Limited (Postcode: B70 8AF) ",
    "fca_link": "https://register.fca.org.uk/ShPo_FirmDetailsPage?id=001b000000MfRslAAF",
    "trading_names": "westbromforintermediaries",
    "ref_number": "303089",
    "status": "Authorised"
  },
  {
    "firm": "Sita Soni (Postcode: B70 6EU) ",
    "fca_link": "https://register.fca.org.uk/ShPo_FirmDetailsPage?id=001b000000m5AKBAA2",
    "trading_names": "Supersound & Light",
    "ref_number": "679268",
    "status": "Authorised"
  },
  {
    "firm": "NATIONWIDE CAR & COMMERCIAL LIMITED (Postcode: B70 6DG) ",
    "fca_link": "https://register.fca.org.uk/ShPo_FirmDetailsPage?id=001b000000j33YaAAI",
    "trading_names": "Nationwide Car and Commercial",
    "ref_number": "668014",
    "status": "Authorised"
  },
  {
    "firm": "RELIANT WINDOWS LIMITED (Postcode: B70 7TN) ",
    "fca_link": "https://register.fca.org.uk/ShPo_FirmDetailsPage?id=001b000003IKmHZAA1",
    "ref_number": "735760",
    "status": "Authorised"
  },
  {
    "firm": "sandwell field sports (Postcode: B70 9EG) ",
    "fca_link": "https://register.fca.org.uk/ShPo_FirmDetailsPage?id=001b000001zwtWlAAI",
    "ref_number": "723629",
    "status": "Authorised"
  },
  {
    "firm": "Global Market Compare Limited (Postcode: B70 8EN) ",
    "fca_link": "https://register.fca.org.uk/ShPo_FirmDetailsPage?id=001b000000NMcPiAAL",
    "ref_number": "600466",
    "status": "Authorised"
  },
  {
    "firm": "I.G. & A.J. Wyle (Postcode: B70 6TL) ",
    "fca_link": "https://register.fca.org.uk/ShPo_FirmDetailsPage?id=001b000000p0CdLAAU",
    "trading_names": "CONFIDENTIAL FINANCE CO",
    "ref_number": "695529",
    "status": "Authorised"
  },
  {
    "firm": "David John Cooper (Postcode: B70 0DA) ",
    "fca_link": "https://register.fca.org.uk/ShPo_FirmDetailsPage?id=001b000000l8c7xAAA",
    "trading_names": "Great Bridge Cars",
    "ref_number": "676005",
    "status": "Authorised"
  },
  {
    "firm": "Cashline Pawnbrokers Limited (Postcode: B70 7AB) ",
    "fca_link": "https://register.fca.org.uk/ShPo_FirmDetailsPage?id=001b000000iA2krAAC",
    "ref_number": "663634",
    "status": "Authorised"
  },
  {
    "firm": "Guest Motors Limited (Postcode: B70 6BY) ",
    "fca_link": "https://register.fca.org.uk/ShPo_FirmDetailsPage?id=001b000000MfOlWAAV",
    "trading_names": "Guest Trucks,Guests Tyre & Auto",
    "ref_number": "310535",
    "status": "Authorised"
  },
  {
    "firm": "C L Mortgages Limited (Postcode: B70 8AF) ",
    "fca_link": "https://register.fca.org.uk/ShPo_FirmDetailsPage?id=001b000000MfRshAAF",
    "trading_names": "Newworld",
    "ref_number": "303084",
    "status": "Authorised"
  },
  {
    "firm": "S R Investments  (WB) Ltd (Postcode: B71 4jz) ",
    "fca_link": "https://register.fca.org.uk/ShPo_FirmDetailsPage?id=001b000000NMZMcAAP",
    "trading_names": "MyStarBuys.co.uk,Southside Insurance,InsureWithTony.co.uk,InsureWithSuresh.co.uk",
    "ref_number": "596395",
    "status": "Authorised"
  }
]