[
  {
    "firm": "Clear Solutions (Wealth and Tax Management) Ltd (Postcode: DE65 5GE) ",
    "fca_link": "https://register.fca.org.uk/ShPo_FirmDetailsPage?id=001b000000MfZ24AAF",
    "trading_names": "Smith Cooper Independent Insurance,Smith Cooper Financial Services Limited",
    "ref_number": "429206",
    "status": "Authorised"
  },
  {
    "firm": "Hilton Garage Ltd (Postcode: DE65 5FJ) ",
    "fca_link": "https://register.fca.org.uk/ShPo_FirmDetailsPage?id=001b000000XnB85AAF",
    "trading_names": "www.hiltongarage.co.uk",
    "ref_number": "627400",
    "status": "Authorised"
  },
  {
    "firm": "Storm Research Limited (Postcode: de65 6ez) ",
    "fca_link": "https://register.fca.org.uk/ShPo_FirmDetailsPage?id=001b000000NMUFdAAP",
    "ref_number": "503911",
    "status": "Authorised"
  },
  {
    "firm": "PREMIER CAR SUPERMARKET LTD (Postcode: DE65 6GY) ",
    "fca_link": "https://register.fca.org.uk/ShPo_FirmDetailsPage?id=001b000000j2YtZAAU",
    "trading_names": "BRAUNSTONE CROSSROADS MOTORS,Braunstone Crossroads Motors Limited",
    "ref_number": "667645",
    "status": "Authorised"
  },
  {
    "firm": "Hi Auto Limited (Postcode: DE65 5FZ) ",
    "fca_link": "https://register.fca.org.uk/ShPo_FirmDetailsPage?id=001b000003MxX3kAAF",
    "trading_names": "Hi-auto,hi! auto,hi-auto",
    "ref_number": "746724",
    "status": "Authorised"
  },
  {
    "firm": "Alfa Funding Ltd (Postcode: DE65 5FJ) ",
    "fca_link": "https://register.fca.org.uk/ShPo_FirmDetailsPage?id=001b000000nyWTrAAM",
    "trading_names": "UK Car Broker",
    "ref_number": "689163",
    "status": "Authorised"
  },
  {
    "firm": "EDM Garage Services Ltd (Postcode: DE65 6BE) ",
    "fca_link": "https://register.fca.org.uk/ShPo_FirmDetailsPage?id=001b000000XnVQdAAN",
    "ref_number": "627401",
    "status": "Authorised"
  },
  {
    "firm": "Madecorn Leisure LLP (Postcode: DE65 6DW) ",
    "fca_link": "https://register.fca.org.uk/ShPo_FirmDetailsPage?id=001b000000h5Ai1AAE",
    "trading_names": "Mercia Marina",
    "ref_number": "659180",
    "status": "Authorised"
  },
  {
    "firm": "Derbyshire Independent Financial Advisers LLP (Postcode: DE65 6AA) ",
    "fca_link": "https://register.fca.org.uk/ShPo_FirmDetailsPage?id=001b000000WBPFIAA5",
    "ref_number": "624915",
    "status": "Authorised"
  },
  {
    "firm": "Archway Motors of Findern Limited (Postcode: DE65 6AX) ",
    "fca_link": "https://register.fca.org.uk/ShPo_FirmDetailsPage?id=001b000002zxj9fAAA",
    "ref_number": "731087",
    "status": "Authorised"
  },
  {
    "firm": "Don Amott Leisure Limited (Postcode: DE65 5FJ) ",
    "fca_link": "https://register.fca.org.uk/ShPo_FirmDetailsPage?id=001b000000m5yGRAAY",
    "trading_names": "Don Amott Leisure Kingdom",
    "ref_number": "679752",
    "status": "Authorised"
  },
  {
    "firm": "Hatton Car Sales Ltd (Postcode: DE65 5DT) ",
    "fca_link": "https://register.fca.org.uk/ShPo_FirmDetailsPage?id=001b000000gA5KgAAK",
    "ref_number": "655454",
    "status": "Authorised"
  }
]