[
  {
    "firm": "K .W. Associates (Postcode: SM4 5DE) ",
    "fca_link": "https://register.fca.org.uk/ShPo_FirmDetailsPage?id=001b000000MfUmmAAF",
    "ref_number": "306383",
    "status": "Authorised"
  },
  {
    "firm": "chandrakumar shanmugalingam (Postcode: SM4 6JH) ",
    "fca_link": "https://register.fca.org.uk/ShPo_FirmDetailsPage?id=001b000002C4myrAAB",
    "trading_names": "chanscars",
    "ref_number": "725542",
    "status": "Authorised"
  },
  {
    "firm": "David John Small (Postcode: SM4 6JS) ",
    "fca_link": "https://register.fca.org.uk/ShPo_FirmDetailsPage?id=001b000000iBkBfAAK",
    "trading_names": "Harlequin Motor Co",
    "ref_number": "664705",
    "status": "Authorised"
  },
  {
    "firm": "Morden Eye Centre (Postcode: SM4 5HP) ",
    "fca_link": "https://register.fca.org.uk/ShPo_FirmDetailsPage?id=001b000000p1OdmAAE",
    "ref_number": "697841",
    "status": "Authorised"
  },
  {
    "firm": "APTIGA LIMITED (Postcode: SM4 4AU) ",
    "fca_link": "https://register.fca.org.uk/ShPo_FirmDetailsPage?id=001b000000j2meRAAQ",
    "trading_names": "BELLS BUSES,GREAT OAK SALES",
    "ref_number": "667852",
    "status": "Authorised"
  },
  {
    "firm": "Merton & Lambeth CAB Ltd (Postcode: SM4 5DA) ",
    "fca_link": "https://register.fca.org.uk/ShPo_FirmDetailsPage?id=001b000000P6Sv4AAF",
    "trading_names": "MERTON AND LAMBETH CITIZENS ADVICE BUREAUX LIMITED",
    "ref_number": "617664",
    "status": "Authorised"
  },
  {
    "firm": "First Financial Options Limited (Postcode: SM4 4QQ) ",
    "fca_link": "https://register.fca.org.uk/ShPo_FirmDetailsPage?id=001b000000NMeDBAA1",
    "ref_number": "578833",
    "status": "Authorised"
  },
  {
    "firm": "Fair Auto Trader Limited (Postcode: SM4 6RW) ",
    "fca_link": "https://register.fca.org.uk/ShPo_FirmDetailsPage?id=001b000003F6jYNAAZ",
    "ref_number": "733161",
    "status": "Authorised"
  },
  {
    "firm": "Mark Henry Treherne (Postcode: SM4 5SQ) ",
    "fca_link": "https://register.fca.org.uk/ShPo_FirmDetailsPage?id=001b000000fUgvNAAS",
    "trading_names": "Heron Veterinary Surgery",
    "ref_number": "653667",
    "status": "Authorised"
  },
  {
    "firm": "X Blade Motor bikes Limited (Postcode: SM4 4AW) ",
    "fca_link": "https://register.fca.org.uk/ShPo_FirmDetailsPage?id=001b000000m6MvmAAE",
    "ref_number": "680015",
    "status": "Authorised"
  },
  {
    "firm": "LUCKY DALE CARS LTD (Postcode: SM4 5AT) ",
    "fca_link": "https://register.fca.org.uk/ShPo_FirmDetailsPage?id=001b000003RENjDAAX",
    "ref_number": "752718",
    "status": "Authorised"
  },
  {
    "firm": "F L C Insurance Services Ltd (Postcode: SM4 4AH) ",
    "fca_link": "https://register.fca.org.uk/ShPo_FirmDetailsPage?id=001b000000MfSsAAAV",
    "ref_number": "314107",
    "status": "Authorised"
  }
]